name_genie/__init__.py
name_genie/alchemy.py
name_genie/book.py
name_genie/clan.py
name_genie/common.py
name_genie/creature.py
name_genie/dao.py
name_genie/material.py
name_genie/name.py
name_genie/nation.py
name_genie/place.py
name_genie/skill.py
name_genie/talisman.py
name_genie/util.py
name_genie-1.0.0.dist-info/LICENSE
name_genie-1.0.0.dist-info/METADATA
name_genie-1.0.0.dist-info/WHEEL
name_genie-1.0.0.dist-info/RECORD
